{
  "target" : {
    "code" : "13317-3",
    "description" : "Staphylococcus aureus.methicillin resistant isolate PrThr Pt Ord Organism specific culture",
    "system" : "loinc"
  },
  "modelName" : "s2-EHR-Node.StaphylococcusaureusmethicillinresistantisolatePrThrPtXXXOrdOrganismspecificculture.v1.0.0.adls",
  "children" : {
    "52969-3" : {
      "source" : {
        "code" : "52969-3",
        "description" : "Staphylococcus aureus.methicillin resistant isolate Nose PrThr Pt Ord Organism specific culture",
        "system" : "loinc"
      },
      "target" : {
        "code" : "13317-3",
        "description" : "Staphylococcus aureus.methicillin resistant isolate PrThr Pt Ord Organism specific culture",
        "system" : "loinc"
      },
      "model" : "s2-EHR-Node.StaphylococcusaureusmethicillinresistantisolatePrThrPtXXXOrdOrganismspecificculture.v1.0.0.adls",
      "descriptors" : [ {
        "key" : {
          "code" : "66746-9",
          "description" : "Specimen type",
          "system" : "loinc"
        },
        "value" : {
          "code" : "447154002",
          "description" : "Specimen from nose",
          "system" : "snomed"
        }
      } ]
    }
  }
}