{
  "target" : {
    "code" : "105073-1",
    "description" : "Megasphaera sp type 1 DNA [Presence] in Specimen",
    "system" : "loinc"
  },
  "modelName" : "Megasphaerasptype1DNAPrThrPtXXXOrd.v1.0.0",
  "children" : {
    "69567-6" : {
      "source" : {
        "code" : "69567-6",
        "description" : "Megasphaera sp type 1 DNA Vag PrThr Pt Ord Probe.amp.tar",
        "system" : "loinc"
      },
      "target" : {
        "code" : "105073-1",
        "description" : "Megasphaera sp type 1 DNA [Presence] in Specimen",
        "system" : "loinc"
      },
      "model" : "Megasphaerasptype1DNAPrThrPtXXXOrd.v1.0.0",
      "descriptors" : [ {
        "key" : {
          "code" : "85069-3",
          "description" : "Lab test method [Type]",
          "system" : "loinc"
        },
        "value" : {
          "code" : "702675006",
          "description" : "Probe with target amplification technique technique",
          "system" : "snomed"
        }
      }, {
        "key" : {
          "code" : "66746-9",
          "description" : "Specimen type",
          "system" : "loinc"
        },
        "value" : {
          "code" : "119394009",
          "description" : "Specimen from vagina",
          "system" : "snomed"
        }
      } ]
    }
  }
}